lsst/__init__.py
lsst/pex/__init__.py
lsst/pex/config/__init__.py
lsst/pex/config/_doNotImportMe.py
lsst/pex/config/callStack.py
lsst/pex/config/choiceField.py
lsst/pex/config/comparison.py
lsst/pex/config/config.py
lsst/pex/config/configChoiceField.py
lsst/pex/config/configDictField.py
lsst/pex/config/configField.py
lsst/pex/config/configurableField.py
lsst/pex/config/convert.py
lsst/pex/config/dictField.py
lsst/pex/config/history.py
lsst/pex/config/listField.py
lsst/pex/config/py.typed
lsst/pex/config/rangeField.py
lsst/pex/config/registry.py
lsst/pex/config/version.py
lsst/pex/config/wrap.py
lsst/pex/config/configurableActions/__init__.py
lsst/pex/config/configurableActions/_configurableAction.py
lsst/pex/config/configurableActions/_configurableActionField.py
lsst/pex/config/configurableActions/_configurableActionStructField.py
lsst/pex/config/configurableActions/tests.py
lsst_pex_config-30.2026.300.dist-info/licenses/COPYRIGHT
lsst_pex_config-30.2026.300.dist-info/licenses/LICENSE
lsst_pex_config-30.2026.300.dist-info/licenses/bsd_license.txt
lsst_pex_config-30.2026.300.dist-info/licenses/gpl-v3.0.txt
lsst_pex_config-30.2026.300.dist-info/METADATA
lsst_pex_config-30.2026.300.dist-info/WHEEL
lsst_pex_config-30.2026.300.dist-info/top_level.txt
lsst_pex_config-30.2026.300.dist-info/zip-safe
lsst_pex_config-30.2026.300.dist-info/RECORD
