Metadata-Version: 2.4
Name: lsst-pex-config
Version: 30.2026.300
Summary: A flexible configuration system using Python files.
Author-email: Rubin Observatory Data Management <dm-admin@lists.lsst.org>
License-Expression: BSD-3-Clause OR GPL-3.0-or-later
Project-URL: Homepage, https://github.com/lsst/pex_config
Keywords: lsst
Classifier: Intended Audience :: Science/Research
Classifier: Operating System :: OS Independent
Classifier: Programming Language :: Python :: 3
Classifier: Programming Language :: Python :: 3.14
Classifier: Programming Language :: Python :: 3.11
Classifier: Programming Language :: Python :: 3.12
Classifier: Programming Language :: Python :: 3.13
Classifier: Topic :: Scientific/Engineering :: Astronomy
Requires-Python: >=3.11.0
License-File: COPYRIGHT
License-File: LICENSE
License-File: gpl-v3.0.txt
License-File: bsd_license.txt
Requires-Dist: pyyaml>=5.1
Requires-Dist: numpy>=1.17
Requires-Dist: lsst-resources
Provides-Extra: test
Requires-Dist: pytest>=3.2; extra == "test"
Requires-Dist: pytest-openfiles>=0.5.0; extra == "test"
Dynamic: license-file
